bpod_core/__init__.py
bpod_core/bpod.py
bpod_core/com.py
bpod_core/fsm.py
bpod_core/ipc.py
bpod_core/misc.py
bpod_core/py.typed
bpod_core-0.1.0a5.dist-info/WHEEL
bpod_core-0.1.0a5.dist-info/METADATA
bpod_core-0.1.0a5.dist-info/RECORD
