Metadata-Version: 2.3
Name: bpod-core
Version: 0.1.0a5
Summary: Python package for interfacing with the Bpod finite state machine
Author: Florian Rau
Author-email: Florian Rau <bimac@users.noreply.github.com>
License: MIT
Classifier: Development Status :: 2 - Pre-Alpha
Classifier: Intended Audience :: Science/Research
Classifier: License :: OSI Approved :: MIT License
Classifier: Operating System :: OS Independent
Classifier: Programming Language :: Python :: 3
Classifier: Topic :: Scientific/Engineering
Classifier: Typing :: Typed
Requires-Dist: numpy
Requires-Dist: pandas
Requires-Dist: pydantic>=2.11
Requires-Dist: pyserial>=3.5
Requires-Dist: graphviz>=0.20.0
Requires-Dist: pyzmq>=27.0.1
Requires-Dist: zeroconf>=0.147.0
Requires-Dist: appdirs>=1.4.4
Requires-Dist: msgspec>=0.19.0
Requires-Dist: packaging>=25.0
Requires-Dist: pyyaml>=6.0.2
Requires-Python: >=3.10
Project-URL: Changelog, https://github.com/int-brain-lab/bpod-core/blob/main/CHANGELOG.md
Project-URL: Documentation, https://int-brain-lab.github.io/bpod-core/
Project-URL: Homepage, https://github.com/int-brain-lab/bpod-core
Project-URL: Issues, https://github.com/int-brain-lab/bpod-core/issues
Project-URL: Repository, https://github.com/int-brain-lab/bpod-core.git
